{
	"miniprogramRoot": "miniprogram/",
	"cloudfunctionRoot": "cloudfunctions/",
	"setting": {
		"urlCheck": false,
		"es6": true,
		"enhance": true,
		"postcss": true,
		"minified": true,
		"newFeature": true,
		"nodeModules": true,
		"autoAudits": false,
		"checkInvalidKey": true,
		"checkSiteMap": true,
		"uploadWithSourceMap": true,
		"babelSetting": {
			"ignore": [],
			"disablePlugins": [],
			"outputPath": ""
		},
		"bundle": true,
		"scopeDataCheck": true
	},
	"appid": "wxbba6b07610fe223a",
	"projectname": "hsf_blog",
	"libVersion": "2.9.4",
	"simulatorType": "wechat",
	"simulatorPluginLibVersion": {},
	"cloudfunctionTemplateRoot": "cloudfunctionTemplate",
	"condition": {
		"search": {
			"current": -1,
			"list": []
		},
		"conversation": {
			"current": -1,
			"list": []
		},
		"plugin": {
			"current": -1,
			"list": []
		},
		"game": {
			"list": []
		},
		"gamePlugin": {
			"current": -1,
			"list": []
		},
		"miniprogram": {
			"current": 0,
			"list": [
				{
					"id": -1,
					"name": "db guide",
					"pathName": "pages/databaseGuide/databaseGuide",
					"query": ""
				},
				{
					"id": -1,
					"name": "pages/messageSelectList/messageSelectList",
					"pathName": "pages/messageSelectList/messageSelectList",
					"query": "",
					"scene": null
				},
				{
					"id": -1,
					"name": "pages/test/test",
					"pathName": "pages/test/test",
					"scene": null
				}
			]
		}
	}
}